kamidana/__init__.py
kamidana/_path.py
kamidana/compat.py
kamidana/data.txt
kamidana/driver.py
kamidana/interfaces.py
kamidana/listinfo.py
kamidana/loader.py
kamidana/additionals/__init__.py
kamidana/additionals/env.py
kamidana/additionals/naming.py
kamidana/additionals/reader.py
kamidana/commands/__init__.py
kamidana/commands/manyfiles.py
kamidana/commands/onefile.py
kamidana/debug/__init__.py
kamidana/debug/_extract.py
kamidana/debug/color.py
kamidana/debug/gentleerror.py
kamidana/extensions/__init__.py
kamidana-0.10.0.dist-info/LICENSE
kamidana-0.10.0.dist-info/METADATA
kamidana-0.10.0.dist-info/WHEEL
kamidana-0.10.0.dist-info/entry_points.txt
kamidana-0.10.0.dist-info/top_level.txt
kamidana-0.10.0.dist-info/RECORD
