Metadata-Version: 2.1
Name: kamidana
Version: 0.10.0
Summary: command line jinja2 template (yet another j2cli)
Home-page: https://github.com/podhmo/kamidana
Author: podhmo
Author-email: ababjam61+github@gmail.com
Keywords: jinja2,cli,commandline
Classifier: Programming Language :: Python
Classifier: Programming Language :: Python :: Implementation :: CPython
License-File: LICENSE
Requires-Dist: jinja2
Requires-Dist: dictknife[load]
Requires-Dist: magicalimport
Requires-Dist: inflection
Provides-Extra: docs
Requires-Dist: sphinx ; extra == 'docs'
Requires-Dist: recommonmark ; extra == 'docs'
Requires-Dist: sphinx-rtd-theme ; extra == 'docs'
Provides-Extra: testing
